LICENSE
MANIFEST.in
setup.py
hankshaw/EnvChangeOutput.py
hankshaw/FitnessOutput.py
hankshaw/GenotypesOutput.py
hankshaw/Metapopulation.py
hankshaw/MetapopulationOutput.py
hankshaw/OutputWriter.py
hankshaw/Population.py
hankshaw/PopulationOutput.py
hankshaw/__init__.py
hankshaw/cmd_script.py
hankshaw/configspec-v1.ini
hankshaw/genome.py
hankshaw/misc.py
hankshaw/topology.py
hankshaw.egg-info/PKG-INFO
hankshaw.egg-info/SOURCES.txt
hankshaw.egg-info/dependency_links.txt
hankshaw.egg-info/entry_points.txt
hankshaw.egg-info/requires.txt
hankshaw.egg-info/top_level.txt