Metadata-Version: 1.1
Name: hankshaw
Version: 2.0.0
Summary: Model for The Evolution of Cooperation by the Hankshaw Effect
Home-page: https://github.com/briandconnelly/hankshaweffect
Author: Brian D. Connelly
Author-email: bdc@bconnelly.net
License: BSD
Keywords: evolution simulation metapopulation
Platform: UNKNOWN
Classifier: Development Status :: 5 - Production/Stable
Classifier: Programming Language :: Python :: 2.7
Classifier: Programming Language :: Python :: 3.4
Classifier: Intended Audience :: Science/Research
Classifier: Topic :: Scientific/Engineering
Classifier: Topic :: Scientific/Engineering :: Artificial Life
Classifier: License :: OSI Approved :: BSD License
